agent_cli/__init__.py
agent_cli/__main__.py
agent_cli/_extras.json
agent_cli/_tools.py
agent_cli/api.py
agent_cli/cli.py
agent_cli/config.py
agent_cli/config_cmd.py
agent_cli/constants.py
agent_cli/docs_gen.py
agent_cli/example-config.toml
agent_cli/opts.py
agent_cli/py.typed
agent_cli/_requirements/.gitkeep
agent_cli/_requirements/audio.txt
agent_cli/_requirements/faster-whisper.txt
agent_cli/_requirements/kokoro.txt
agent_cli/_requirements/llm.txt
agent_cli/_requirements/memory.txt
agent_cli/_requirements/mlx-whisper.txt
agent_cli/_requirements/piper.txt
agent_cli/_requirements/rag.txt
agent_cli/_requirements/server.txt
agent_cli/_requirements/speed.txt
agent_cli/_requirements/vad.txt
agent_cli/_requirements/wyoming.txt
agent_cli/agents/__init__.py
agent_cli/agents/_voice_agent_common.py
agent_cli/agents/assistant.py
agent_cli/agents/autocorrect.py
agent_cli/agents/chat.py
agent_cli/agents/rag_proxy.py
agent_cli/agents/speak.py
agent_cli/agents/transcribe.py
agent_cli/agents/transcribe_daemon.py
agent_cli/agents/voice_edit.py
agent_cli/agents/memory/__init__.py
agent_cli/agents/memory/add.py
agent_cli/agents/memory/proxy.py
agent_cli/core/__init__.py
agent_cli/core/audio.py
agent_cli/core/audio_format.py
agent_cli/core/chroma.py
agent_cli/core/deps.py
agent_cli/core/openai_proxy.py
agent_cli/core/process.py
agent_cli/core/reranker.py
agent_cli/core/sse.py
agent_cli/core/transcription_logger.py
agent_cli/core/utils.py
agent_cli/core/vad.py
agent_cli/core/watch.py
agent_cli/dev/__init__.py
agent_cli/dev/cli.py
agent_cli/dev/project.py
agent_cli/dev/registry.py
agent_cli/dev/worktree.py
agent_cli/dev/coding_agents/__init__.py
agent_cli/dev/coding_agents/aider.py
agent_cli/dev/coding_agents/base.py
agent_cli/dev/coding_agents/claude.py
agent_cli/dev/coding_agents/codex.py
agent_cli/dev/coding_agents/continue_dev.py
agent_cli/dev/coding_agents/copilot.py
agent_cli/dev/coding_agents/cursor_agent.py
agent_cli/dev/coding_agents/gemini.py
agent_cli-0.72.4.dist-info/METADATA
agent_cli-0.72.4.dist-info/WHEEL
agent_cli-0.72.4.dist-info/entry_points.txt
agent_cli-0.72.4.dist-info/licenses/LICENSE
agent_cli-0.72.4.dist-info/RECORD
