Metadata-Version: 2.4
Name: agent-cli
Version: 0.72.4
Summary: A suite of AI-powered command-line tools for text correction, audio transcription, and voice assistance.
Project-URL: Homepage, https://github.com/basnijholt/agent-cli
Author-email: Bas Nijholt <bas@nijho.lt>
License-File: LICENSE
Requires-Python: <3.14,>=3.11
Requires-Dist: dotenv
Requires-Dist: httpx
Requires-Dist: psutil; sys_platform == 'win32'
Requires-Dist: pydantic
Requires-Dist: pyperclip
Requires-Dist: rich
Requires-Dist: setproctitle
Requires-Dist: typer
Requires-Dist: typer-slim[standard]
Provides-Extra: audio
Requires-Dist: numpy; extra == 'audio'
Requires-Dist: sounddevice>=0.4.6; extra == 'audio'
Requires-Dist: wyoming>=1.5.2; extra == 'audio'
Provides-Extra: dev
Requires-Dist: markdown-code-runner>=2.7.0; extra == 'dev'
Requires-Dist: markdown-gfm-admonition; extra == 'dev'
Requires-Dist: notebook; extra == 'dev'
Requires-Dist: pre-commit-uv>=4.1.4; extra == 'dev'
Requires-Dist: pre-commit>=3.0.0; extra == 'dev'
Requires-Dist: pylint>=3.0.0; extra == 'dev'
Requires-Dist: pytest-asyncio>=0.20.0; extra == 'dev'
Requires-Dist: pytest-cov>=4.0.0; extra == 'dev'
Requires-Dist: pytest-mock; extra == 'dev'
Requires-Dist: pytest-timeout; extra == 'dev'
Requires-Dist: pytest>=7.0.0; extra == 'dev'
Requires-Dist: ruff; extra == 'dev'
Requires-Dist: versioningit; extra == 'dev'
Requires-Dist: zensical; extra == 'dev'
Provides-Extra: faster-whisper
Requires-Dist: fastapi[standard]; extra == 'faster-whisper'
Requires-Dist: faster-whisper>=1.0.0; extra == 'faster-whisper'
Provides-Extra: kokoro
Requires-Dist: fastapi[standard]; extra == 'kokoro'
Requires-Dist: huggingface-hub>=0.20.0; extra == 'kokoro'
Requires-Dist: kokoro>=0.9.0; extra == 'kokoro'
Requires-Dist: pip; extra == 'kokoro'
Requires-Dist: soundfile>=0.12.0; extra == 'kokoro'
Requires-Dist: transformers>=4.40.0; extra == 'kokoro'
Provides-Extra: llm
Requires-Dist: pydantic-ai-slim[duckduckgo,google,openai,vertexai]>=0.1.1; extra == 'llm'
Provides-Extra: memory
Requires-Dist: chromadb>=0.4.22; extra == 'memory'
Requires-Dist: fastapi[standard]; extra == 'memory'
Requires-Dist: huggingface-hub>=0.20.0; extra == 'memory'
Requires-Dist: onnxruntime>=1.17.0; extra == 'memory'
Requires-Dist: openai>=1.0.0; extra == 'memory'
Requires-Dist: pyyaml>=6.0.0; extra == 'memory'
Requires-Dist: transformers>=4.30.0; extra == 'memory'
Requires-Dist: watchfiles>=0.21.0; extra == 'memory'
Provides-Extra: mlx-whisper
Requires-Dist: fastapi[standard]; (sys_platform == 'darwin' and platform_machine == 'arm64') and extra == 'mlx-whisper'
Requires-Dist: mlx-whisper>=0.4.0; (sys_platform == 'darwin' and platform_machine == 'arm64') and extra == 'mlx-whisper'
Provides-Extra: piper
Requires-Dist: fastapi[standard]; extra == 'piper'
Requires-Dist: piper-tts>=1.2.0; extra == 'piper'
Provides-Extra: rag
Requires-Dist: chromadb>=0.4.22; extra == 'rag'
Requires-Dist: fastapi[standard]; extra == 'rag'
Requires-Dist: huggingface-hub>=0.20.0; extra == 'rag'
Requires-Dist: markitdown[docx,pdf,pptx]>=0.1.3; extra == 'rag'
Requires-Dist: onnxruntime>=1.17.0; extra == 'rag'
Requires-Dist: openai>=1.0.0; extra == 'rag'
Requires-Dist: transformers>=4.30.0; extra == 'rag'
Requires-Dist: watchfiles>=0.21.0; extra == 'rag'
Provides-Extra: server
Requires-Dist: fastapi[standard]; extra == 'server'
Provides-Extra: speed
Requires-Dist: audiostretchy>=1.3.0; extra == 'speed'
Provides-Extra: test
Requires-Dist: pytest-asyncio>=0.20.0; extra == 'test'
Requires-Dist: pytest-cov>=4.0.0; extra == 'test'
Requires-Dist: pytest-mock; extra == 'test'
Requires-Dist: pytest-timeout; extra == 'test'
Requires-Dist: pytest>=7.0.0; extra == 'test'
Provides-Extra: vad
Requires-Dist: silero-vad-lite>=0.2.1; extra == 'vad'
Provides-Extra: wyoming
Requires-Dist: wyoming>=1.5.2; extra == 'wyoming'
